asciistuff/VERSION.txt
asciistuff/__common__.py
asciistuff/__info__.py
asciistuff/__init__.py
asciistuff/banner.py
asciistuff/cowsay.py
asciistuff/file.py
asciistuff/fonts.txt
asciistuff/image.py
asciistuff/lolcat.py
asciistuff/quote.py
asciistuff-1.3.3.dist-info/licenses/LICENSE
asciistuff-1.3.3.dist-info/METADATA
asciistuff-1.3.3.dist-info/WHEEL
asciistuff-1.3.3.dist-info/entry_points.txt
asciistuff-1.3.3.dist-info/top_level.txt
asciistuff-1.3.3.dist-info/RECORD
