Metadata-Version: 2.4
Name: asciistuff
Version: 1.3.3
Summary: Library for producing ASCII arts from a text or an image
Author-email: Alexandre D'Hondt <alexandre.dhondt@gmail.com>
License:                     GNU GENERAL PUBLIC LICENSE
Project-URL: documentation, https://python-asciistuff.readthedocs.io/en/latest/?badge=latest
Project-URL: homepage, https://github.com/dhondta/python-asciistuff
Project-URL: issues, https://github.com/dhondta/python-asciistuff/issues
Project-URL: repository, https://github.com/dhondta/python-asciistuff
Keywords: python,development,programming,ascii-art,banner-generator,quote-generator,cowsay
Classifier: Development Status :: 5 - Production/Stable
Classifier: Environment :: Console
Classifier: Intended Audience :: Developers
Classifier: License :: OSI Approved :: GNU General Public License v3 or later (GPLv3+)
Classifier: Programming Language :: Python :: 3
Classifier: Topic :: Software Development :: Libraries :: Python Modules
Requires-Python: <4,>=3.8
License-File: LICENSE
Requires-Dist: colorama
Requires-Dist: cowpy>=1.1.5
Requires-Dist: pillow>=11.2.0
Requires-Dist: PyFiglet>=1.0.3
Dynamic: license-file
